{"cameraMode":{"drawMode":0,"name":"Shaded","section":"Shading Mode"},"sceneLighting":true,"audioPlay":false,"sceneViewState":{"m_AlwaysRefresh":false,"showFog":true,"showSkybox":true,"showFlares":true,"showImageEffects":true,"showParticleSystems":true,"showVisualEffectGraphs":true,"m_FxEnabled":true},"in2DMode":false,"pivot":{"x":551.2932739257813,"y":1174.71044921875,"z":0.0},"rotation":{"x":-0.09521147608757019,"y":-0.03374389931559563,"z":0.003236285410821438,"w":-0.9948946833610535},"size":372.3047790527344,"orthographic":true}